dotwiz/__init__.py
dotwiz/__version__.py
dotwiz/common.py
dotwiz/common.pyi
dotwiz/main.py
dotwiz/main.pyi
dotwiz/plus.py
dotwiz/plus.pyi
dotwiz/py.typed
dotwiz-0.4.0.dist-info/LICENSE
dotwiz-0.4.0.dist-info/METADATA
dotwiz-0.4.0.dist-info/WHEEL
dotwiz-0.4.0.dist-info/top_level.txt
dotwiz-0.4.0.dist-info/RECORD
