Metadata-Version: 2.1
Name: dotwiz
Version: 0.4.0
Summary: DotWiz is a blazing fast dict subclass that enables accessing (nested) keys in dot notation.
Home-page: https://github.com/rnag/dotwiz
Author: Ritvik Nag
Author-email: rv.kvetch@gmail.com
License: MIT
Project-URL: Documentation, https://dotwiz.readthedocs.io
Project-URL: Source, https://github.com/rnag/dotwiz
Keywords: dot,dict,dotted,dotdict,map,access,dynamic,attribute,attr,dotwiz
Platform: UNKNOWN
Classifier: Development Status :: 4 - Beta
Classifier: Intended Audience :: Developers
Classifier: License :: OSI Approved :: MIT License
Classifier: Natural Language :: English
Classifier: Programming Language :: Python :: 3 :: Only
Classifier: Programming Language :: Python :: 3
Classifier: Programming Language :: Python :: 3.7
Classifier: Programming Language :: Python :: 3.8
Classifier: Programming Language :: Python :: 3.9
Classifier: Programming Language :: Python :: 3.10
Classifier: Programming Language :: Python
Requires-Dist: pyheck (==0.1.5)
